{
  "experiment": {
    "goal": "test",
    "device": "cuda",
    "device_id": "0",
    "runs": 1,
    "seed": 1
  },
  "federation": {
    "algorithm": "FedGFE",
    "num_clients": 1,
    "global_rounds": 100,
    "local_epochs": 10,
    "join_ratio": 1.0,
    "eval_gap": 5,
    "model_aggregation": "fedavg"
  },
  "model": {
    "backbone": "vit",
    "backbone_model": "hf_vit",
    "pretrained": false,
    "num_classes": 2,
    "embedding_size": 768,
    "patch_size": 16
  },
  "training": {
    "optimizer": "AdamW",
    "learning_rate": 0.005,
    "batch_size": 16,
    "weight_decay": 0.001,
    "momentum": 0.9,
    "learning_rate_schedule": false
  },
  "dataset": {
    "name": "ShenzenMontogmery-1N-ClaSeg",
    "image_size": 224
  },
  "fedgfe": {
    "nodes_downstream_tasks": "classification",
    "nodes_pretext_tasks": "",
    "nodes_training_sequence": "downstream",
    "cls_token_only": false,
    "patch_size": 16
  },
  "nodes_tasks": {
    "0": {
      "task_type": "classification",
      "pretext_tasks": [ "byod", "image_rotation" ],
      "dataset": "ShenzenMontogmery-1N-ClaSeg",
      "dataset_split": "0"
    },
    "1": {
      "task_type": "segmentation",
      "pretext_tasks": [ "patch_masking" ],
      "dataset": "ShenzenMontogmery-1N-ClaSeg",
      "dataset_split": "0"
    }
  },
  "wandb": {
    "disabled": true
  }
}